{"ret_num":1574,"ret_array":[{"_id":32950454731,"_score":1,"_type":"vertex","_visited_num":1,"definition":["1.\u3014\uff5e\uff5e\u3015\u5f62\u5bb9\u660f\u82b1\u8ff7\u79bb\u3002 2.\u95ed\u773c\uff1a\uff5e\u76ee\uff08\u4ea6\u6307\u4eba\u6b7b\u65f6\u5fc3\u91cc\u65e0\u7275\u6302\uff09\u3002\u6b7b\u4e0d\uff5e\u76ee\u3002"],"line_type":["\u6c34"],"name":["\u7791"],"pinyin":["m\u00edng"],"radicals":["\u76ee"],"sid":["57ed361e47d1441d8c668254572ce287"],"stroke_count":["15"],"type":["word"]},{"_id":34191974569,"_score":1,"_type":"vertex","_visited_num":1,"definition":["\u3014\uff5e\u7b95\u3015\u7528\u6728\u3001\u7af9\u3001\u94c1\u7247\u505a\u6210\u7684\u64ae\u5783\u573e\u3001\u7cae\u98df\u7b49\u7684\u5668\u5177\u3002"],"line_type":["\u6c34"],"name":["\u755a"],"pinyin":["b\u011bn"],"radicals":["\u7530"],"sid":["45b742b8aed04710a7f14af117b3191f"],"stroke_count":["10"],"type":["word"]},{"_id":31423735190,"_score":1,"_type":"vertex","_visited_num":1,"definition":["\u3014\uff5e\u5dde\u3015\u5730\u540d\uff0c\u5728\u5b89\u5fbd\u7701\u3002"],"line_type":["\u6c34"],"name":["\u4eb3"],"pinyin":["b\u00f3"],"radicals":["\u4ea0"],"sid":["9ebba49a4f424725b6f4022d9614216d"],"stroke_count":["10"],"type":["word"]},{"_id":34191977219,"_score":1,"_type":"vertex","_visited_num":1,"definition":["1.\u9189\uff1a\u5fae\uff5e\u3002\u9189\uff5e\uff5e\u3002 2.\u53e4\u540c\u201c\u718f\u201d\uff0c\u718f\u67d3\u3002"],"line_type":["\u6c34"],"name":["\u91ba"],"pinyin":["x\u016bn"],"radicals":["\u9149"],"sid":["9802e26293ef40cc81714c2cee43978c"],"stroke_count":["21"],"type":["word"]},{"_id":33353110182,"_score":1,"_type":"vertex","_visited_num":1,"definition":["1.\u9006\u7740\u6c34\u6d41\u7684\u65b9\u5411\u8d70\uff1a\uff5e\u6d41\u800c\u4e0a\u3002 2.\u8ffd\u6c42\u6839\u6e90\u6216\u56de\u60f3\uff1a\u56de\uff5e\u3002\u8ffd\uff5e\u3002\u4e0a\uff5e\u3002\u8ffd\u672c\uff5e\u6e90\u3002"],"line_type":["\u6c34"],"name":["\u6eaf"],"pinyin":["s\u00f9"],"sid":["49e8d94f427711e5a2d0c8e0eb15ce01"],"stroke_count":["13"],"type":["word"]},{"_id":34040976049,"_score":1,"_type":"vertex","_visited_num":1,"definition":["[m\u00ed]\uff1a1.\u7ca5\uff1a\u8089\uff5e\u3002\uff5e\u6cb8\uff08\u5f62\u5bb9\u6df7\u4e71\u7eb7\u6270\uff09\u3002 2.\u70c2\uff0c\u788e\uff1a\uff5e\u70c2\u3002\uff5e\u8eaf\uff08\u727a\u7272\u751f\u547d\uff09\u3002\uff5e\u706d\u3002 3.\u6d6a\u8d39\uff1a\uff5e\u8d39\u3002 4.\u59d3\u3002 [m\u00e9i]\uff1a\u4e0d\u9ecf\u7684\u9ecd\uff08\u4ea6\u79f0\u201c\u7a44\u201d\uff09\uff1a\uff5e\u5b50\u3002\uff5e\u9ecd\u3002\uff5e\u5b50\u9762\u3002"],"line_type":["\u6c34"],"name":["\u7cdc"],"pinyin":["m\u00ed","m\u00e9i"],"sid":["49f326cc427711e5bf53c8e0eb15ce01"],"stroke_count":["17"],"type":["word"]},{"_id":31943824574,"_score":1,"_type":"vertex","_visited_num":1,"definition":["\u3014\u7425\uff5e\u3015\u89c1\u201c\u7425\u201d\u3002"],"line_type":["\u6c34"],"name":["\u73c0"],"pinyin":["p\u00f2"],"radicals":["\u738b"],"sid":["73a5c69c9186452491b40365124d4a06"],"stroke_count":["9"],"type":["word"]},{"_id":30668759871,"_score":1,"_type":"vertex","_visited_num":1,"definition":["[d\u00e0n]\uff1a1.\u606c\u9759\u3001\u5b89\u7136\u7684\u6837\u5b50\uff1a\uff5e\u6cca\u3002\uff5e\u6f20\u3002\uff5e\u8584\u3002\u606c\uff5e\u3002 2.\u6c34\u6ce2\u7ea1\u7f13\u7684\u6837\u5b50\uff1a\uff5e\u6de1\u3002\uff5e\uff5e\u3002 [t\u00e1n]\uff1a\u3014\uff5e\u53f0\u3015\u590d\u59d3\u3002"],"line_type":["\u6c34"],"name":["\u6fb9"],"pinyin":["d\u00e0n","t\u00e1n"],"radicals":["\u6c35"],"sid":["7002fcf8b43640a3bba33338ee438a1d"],"stroke_count":["16"],"type":["word"]},{"_id":30299661631,"_score":1,"_type":"vertex","_visited_num":1,"definition":["1.\u53e4\u4ee3\u6307\u6325\u519b\u961f\u7684\u65d7\u5b50\uff1a\uff5e\u4e0b\u3002 2.\u6307\u6325\uff1a\uff5e\u519b\u524d\u8fdb\u3002"],"line_type":["\u6c34"],"name":["\u9ebe"],"pinyin":["hu\u012b"],"radicals":["\u9ebb"],"sid":["ecdd517546fe4ece8b12092c6246f9a8"],"stroke_count":["15"],"type":["word"]},{"_id":33806101323,"_score":1,"_type":"vertex","_visited_num":1,"definition":["1.\u5230\uff0c\u81f3\uff1a\u8d77\uff5e\u3002\uff5e\u4eca\u3002 2.\u59cb\u7ec8\uff08\u7528\u4e8e\u201c\u672a\u201d\u6216\u201c\u65e0\u201d\u524d\uff09\uff1a\uff5e\u672a\u6210\u529f\u3002\uff5e\u65e0\u97f3\u4fe1\u3002"],"line_type":["\u6c34"],"name":["\u8fc4"],"pinyin":["q\u00ec"],"radicals":["\u8fb6"],"sid":["6afd287606c54775a1035dac4eaf5ef2"],"stroke_count":["6"],"type":["word"]},{"_id":31927042989,"_score":1,"_type":"vertex","_visited_num":1,"definition":["1.\u5b50\u5b9e\u4e0d\u9971\u6ee1\uff1a\uff5e\u5b50\uff08\u4e0d\u9971\u6ee1\u7684\u5b50\u5b9e\uff09\u3002\uff5e\u7ce0\uff08\u79d5\u5b50\u548c\u7ce0\uff0c\u55bb\u6ca1\u6709\u4ef7\u503c\u7684\u4e1c\u897f\uff09\u3002 2.\u574f\uff0c\u4e0d\u826f\uff1a\uff5e\u653f\uff08\u4e0d\u826f\u7684\u653f\u6cbb\u63aa\u65bd\uff09\u3002 3.\u53e4\u540c\u201c\u7eb0\u201d\uff0c\u7eb0\u8c2c\u3002"],"line_type":["\u6c34"],"name":["\u79d5"],"pinyin":["b\u01d0"],"radicals":["\u79be"],"sid":["698f7824a05b4e3ebeb91fd5cb5b9b51"],"stroke_count":["9"],"type":["word"]},{"_id":33051116752,"_score":1,"_type":"vertex","_visited_num":1,"definition":["1.\u5bf9\u4e8b\u7269\u7684\u504f\u7231\u6210\u4e3a\u4e60\u60ef\uff1a\uff5e\u4e60\u3002\uff5e\u597d\uff08h\u00e0o\uff09\u3002\uff5e\u6027\u3002\uff5e\u7231\u3002\uff5e\u75fc\uff08\u4e45\u6cbb\u4e0d\u6108\u7684\u75be\u75c5\uff09\u3002\u6d01\uff5e\u3002 2.\u4e2d\u533b\u6307\u996e\u6c34\u4e0d\u6d88\u7684\u75c5\u3002 3.\u53e4\u540c\u201c\u75de\u201d\uff0c\u75de\u5757\u3002"],"line_type":["\u6c34"],"name":["\u7656"],"pinyin":["p\u01d0"],"radicals":["\u7592"],"sid":["b18277f0b20e4d7795bc51ab39433b8e"],"stroke_count":["18"],"type":["word"]},{"_id":32614916421,"_score":1,"_type":"vertex","_visited_num":1,"definition":["\u8c61\u58f0\u8bcd\uff0c\u7f8a\u53eb\u7684\u58f0\u97f3\u3002"],"line_type":["\u6c34"],"name":["\u54a9"],"pinyin":["mi\u0113"],"radicals":["\u53e3"],"sid":["b76e0ab3b7a9403a90e9c04b961eede0"],"stroke_count":["9"],"type":["word"]},{"_id":30349992880,"_score":1,"_type":"vertex","_visited_num":1,"definition":["\u3014\u6591\uff5e\u3015\u6606\u866b\uff0c\u817f\u7ec6\u957f\uff0c\u9798\u7fc5\u4e0a\u9ec4\u9ed1\u8272\u6591\u7eb9\uff0c\u6210\u866b\u5371\u5bb3\u519c\u4f5c\u7269\uff0c\u53ef\u5165\u836f\u3002"],"line_type":["\u6c34"],"name":["\u8765"],"pinyin":["m\u00e1o"],"radicals":["\u866b"],"sid":["9702cea84f054334bb77caa8a8b7de65"],"stroke_count":["15"],"type":["word"]},{"_id":30903632904,"_score":1,"_type":"vertex","_visited_num":1,"definition":["1.\u5468\uff0c\u7ed5\u4e00\u5708\uff1a\u7ed5\u6811\u4e09\uff5e\u3002 2.\u73af\u7ed5\uff0c\u6ee1\uff1a\uff5e\u6708\u3002\u67f3\u836b\uff5e\u5730\u3002"],"line_type":["\u6c34"],"name":["\u531d"],"pinyin":["z\u0101"],"radicals":["\u531a"],"sid":["5cf8c33cf30d40e6be7e1c240159dc76"],"stroke_count":["5"],"type":["word"]},{"_id":31155296861,"_score":1,"_type":"vertex","_visited_num":1,"definition":["\u3014\uff5e\u6cb3\u3015\u6c34\u540d\uff0c\u6e90\u51fa\u4e2d\u56fd\u5b89\u5fbd\u7701\uff0c\u6d41\u81f3\u6c5f\u82cf\u7701\u5165\u957f\u6c5f\u3002"],"line_type":["\u6c34"],"name":["\u6ec1"],"pinyin":["ch\u00fa"],"radicals":["\u6c35"],"sid":["7d225b918d954798932d687e4778d561"],"stroke_count":["12"],"type":["word"]},{"_id":31692165588,"_score":1,"_type":"vertex","_visited_num":1,"definition":["1.\u53e4\u4ee3\u7687\u5bab\u91cc\u7684\u5973\u5b98\uff0c\u7687\u5e1d\u7684\u59be\uff0c\u4f8d\u4ece\uff1a\u5983\uff5e\u3002\uff5e\u5987\u3002\uff5e\u5fa1\u3002\uff5e\u5af1\u3002 2.\u53e4\u4ee3\u59bb\u6b7b\u540e\u4e4b\u79f0\u3002 3.\u3014\uff5e\u4fea\u3015\u4f09\u4fea\uff0c\u914d\u5076\u3002 4.\u53e4\u540c\u201c\u7f24\u201d\uff0c\u4f17\u591a\u7684\u6837\u5b50\u3002"],"line_type":["\u6c34"],"name":["\u5ad4"],"pinyin":["p\u00edn"],"radicals":["\u5973"],"sid":["c995008b20ac4c5aad48f49fcafc1ff0"],"stroke_count":["13"],"type":["word"]},{"_id":32229033045,"_score":1,"_type":"vertex","_visited_num":1,"definition":["[j\u00f9n]\uff1a1.\u758f\u901a\uff0c\u6316\u6df1\uff1a\u758f\uff5e\u3002\uff5e\u6cb3\u3002\uff5e\u6ce5\u8239\u3002 2.\u6df1\uff1a\uff5e\u54f2\uff08\u6df1\u6c89\u800c\u6709\u667a\u6167\uff09\u3002 3.\u6398\u53d6\uff0c\u69a8\u53d6\u3002 [x\u00f9n]\uff1a\u3014\uff5e\u53bf\u3015\u5730\u540d\uff0c\u5728\u4e2d\u56fd\u6cb3\u5357\u7701\u3002"],"line_type":["\u6c34"],"name":["\u6d5a"],"pinyin":["j\u00f9n","x\u00f9n"],"radicals":["\u6c35"],"sid":["63030a9f0fd146a6aef08d841edcb04c"],"stroke_count":["10"],"type":["word"]},{"_id":30568091270,"_score":1,"_type":"vertex","_visited_num":1,"definition":["1.\u5b8c\u7ed3\uff0c\u7ec8\u4e86\uff1a\u6536\uff5e\u3002\u4ed8\uff5e\u3002 2.\u622a\u6b62\uff1a\u8d77\uff5e\u3002"],"line_type":["\u6c34"],"name":["\u8bab"],"pinyin":["q\u00ec"],"radicals":["\u8ba0"],"sid":["7881e7ccee8c47c0bbbb5ab8352a71ad"],"stroke_count":["5"],"type":["word"]},{"_id":32178712852,"_score":1,"_type":"vertex","_visited_num":1,"definition":["[pi\u01ceo]\uff1a1.\u9752\u767d\u8272\uff0c\u6de1\u9752\u3002 2.\u9752\u767d\u8272\u7684\u4e1d\u7ec7\u54c1\uff1a\uff5e\u5e19\uff08\u4e66\u8863\uff0c\u4ea6\u6307\u4e66\u5377\uff09\u3002 [pi\u0101o]\uff1a1.\u3014\uff5e\u7f08\u3015\u5f62\u5bb9\u9690\u9690\u7ea6\u7ea6\uff0c\u82e5\u6709\u82e5\u65e0\uff0c\u5982\u201c\u865a\u65e0\uff5e\uff5e\u201d\u3002\u4ea6\u4f5c\u201c\u98d8\u6e3a\u201d\u3002 2.\u3014\uff5e\uff5e\u3015\u8f7b\u8f7b\u98de\u8d77\u6765\u7684\u6837\u5b50\u3002 3.\uff08\u7e39\uff09"],"line_type":["\u6c34"],"name":["\u7f25"],"pinyin":["pi\u01ceo","pi\u0101o"],"radicals":["\u7e9f"],"sid":["867e21fbbff0422f8b6bda218bc54d75"],"stroke_count":["14"],"type":["word"]}],"ret_type":"multiword","hilight":{"radicals":"all","strokes":"all","line_type":"\u6c34"},"page_total":79,"tag":{"tagLists":{"radicals":["\u5168\u90e8","\u6c35<span>(\u5e38\u89c1)<\/span>","\u6728","\u8279","\u53e3","\u624c","\u9485","\u4ebb","\u5973","\u866b","\u571f","\u8ba0","\u5fc4","\u706b","\u7e9f","\u7af9","\u5c71","\u6708","\u961d","\u77f3","\u4e00<span>(1\u753b)<\/span>","\u4e3f","\u4e59","\u4e28","\u4e5a","\u4e36","\u4e85","\u5202<span>(2\u753b)<\/span>","\u529b","\u51ab","\u5382","\u531a","\u4eba","\u4ea0","\u5341","\u5200","\u52f9","\u53c8","\u5196","\u5182","\u516b","\u513f","\u4e8c","\u5369","\u53b6","\u51e0","\u51f5","\u4e37","\u5ef4","\u535c","\u5165","\u5315","\u5338","\u8fb6<span>(3\u753b)<\/span>","\u72ad","\u5b80","\u5e7f","\u5dfe","\u5f73","\u5927","\u56d7","\u9a6c","\u5f13","\u5c38","\u9963","\u95e8","\u5b50","\u58eb","\u5bf8","\u5915","\u5c0f","\u5f61","\u5902","\u5c22","\u5efe","\u5de5","\u5df3","\u5f0b","\u5f50","\u5e72","\u5f51","\u5ddb","\u5e7a","\u5df1","\u5140","\u98de","\u5ddd","\u5c6e","\u738b<span>(4\u753b)<\/span>","\u65e5","\u5fc3","\u793b","\u8d1d","\u6b20","\u6535","\u725c","\u6b79","\u6bdb","\u8f66","\u74e6","\u6208","\u6c34","\u624b","\u706c","\u65b9","\u6c14","\u6bb3","\u6b62","\u66f0","\u65a4","\u6237","\u725b","\u72ac","\u89c1","\u6534","\u7247","\u6587","\u6597","\u98ce","\u8002","\u723f","\u722b","\u6bd4","\u97e6","\u722a","\u6c0f","\u652f","\u5384","\u7236","\u6bcb","\u65e1","\u723b","\u5c23","\u7259","\u8080","\u535d","\u957f","\u76ee<span>(5\u753b)<\/span>","\u9485","\u7592","\u8864","\u79be","\u7530","\u7a74","\u9e1f","\u76bf","\u7f52","\u7acb","\u767d","\u793a","\u76ae","\u77e2","\u7389","\u74dc","\u751f","\u7528","\u7518","\u758b","\u77db","\u7676","\u6bcd","\u7384","\u9f99","\u4e1a","\u6b7a","\u7c73<span>(6\u753b)<\/span>","\u821f","\u8033","\u7fbd","\u8863","\u9875","\u7cf9","\u7cf8","\u7f8a","\u8012","\u864d","\u7f36","\u884c","\u81fc","\u820c","\u8840","\u8089","\u8980","\u81ea","\u81f3","\u807f","\u81e3","\u8272","\u800c","\u826e","\u8278","\u7f51","\u9f50","\u5148","\u897f","\u8a00<span>(7\u753b)<\/span>","\u8db3","\u8eca","\u8c9d","\u9149","\u8d70","\u898b","\u89d2","\u8c78","\u8c55","\u8eab","\u8f9b","\u8c46","\u8c37","\u8d64","\u9091","\u9578","\u514b","\u8fb0","\u91cc","\u9ea6","\u5364","\u8fb5","\u91d2<span>(8\u753b)<\/span>","\u98e0","\u96e8","\u9c7c","\u9580","\u96b9","\u91d1","\u9f7f","\u9752","\u91c7","\u975e","\u96b6","\u9577","\u961c","\u9763","\u9751","\u9801<span>(9\u753b)<\/span>","\u9769","\u9aa8","\u98a8","\u9b3c","\u97cb","\u9999","\u97f3","\u9762","\u97ed","\u9996","\u98df","\u99ac<span>(10\u753b)<\/span>","\u9adf","\u9b25","\u9b32","\u9ad8","\u9b2f","\u9ce5<span>(11\u753b)<\/span>","\u9b5a","\u9e7f","\u9ea5","\u9ec4","\u9e75","\u9ebb","\u9ed1<span>(12\u753b)<\/span>","\u9efd","\u9f0e","\u9ef9","\u9ecd","\u9f20<span>(\u66f4\u591a)<\/span>","\u9f13","\u9f3b","\u9f4a","\u9f52","\u9f8d","\u9fa0"],"strokes":["\u5168\u90e8","1\u753b","2\u753b","3\u753b","4\u753b","5\u753b","6\u753b","7\u753b","8\u753b","9\u753b","10\u753b","11\u753b","12\u753b","13\u753b","14\u753b","15\u753b","16\u753b","17\u753b","18\u753b","19\u753b","20\u753b","21\u753b","22\u753b","23\u753b","24\u753b","25\u753b","26\u753b","27\u753b","28\u753b","29\u753b","30\u753b","31\u753b","32\u753b","33\u753b","34\u753b","35\u753b","36\u753b","37\u753b","38\u753b","39\u753b","40\u753b","41\u753b","42\u753b","43\u753b","44\u753b","45\u753b","46\u753b","47\u753b","48\u753b"],"line_type":["\u5168\u90e8","\u91d1","\u6728","\u6c34","\u706b","\u571f"]},"nameMapping":{"radicals":"\u90e8\u9996","strokes":"\u7b14\u753b","line_type":"\u4e94\u884c"},"activeTags":{"radicals":["\u5168\u90e8"],"strokes":["\u5168\u90e8"],"line_type":["\u6c34"]}},"result_type":"zici"}