{"ret_num":1503,"ret_array":[{"_id":30500983101,"_score":1,"_type":"vertex","_visited_num":1,"definition":["1.\u9ad8\u8d77\uff0c\u76f4\u7acb\uff1a\u9ad8\uff5e\u5165\u4e91\u3002\uff5e\u7acb\u3002\uff5e\u62d4\u3002\uff5e\u5cd9\u3002 2.\u60ca\u52a8\uff1a\uff5e\u52a8\u3002\uff5e\u4eba\u542c\u95fb\u3002 3.\u804b\uff1a\uff5e\u6627\uff08\u53c8\u804b\u53c8\u778e\uff0c\u5f15\u7533\u4e3a\u660f\u8069\uff09\u3002"],"line_type":["\u91d1"],"name":["\u8038"],"pinyin":["s\u01d2ng"],"radicals":["\u8033"],"sid":["4a4ac3586a6d4cb3aad1bb6b9d117cf1"],"stroke_count":["10"],"type":["word"]},{"_id":33286001284,"_score":1,"_type":"vertex","_visited_num":1,"definition":["[n\u00edng]\uff1a1.\u63e1\u4f4f\u7269\u4f53\u7684\u4e24\u7aef\u5411\u76f8\u53cd\u7684\u65b9\u5411\u7528\u529b\uff1a\uff5e\u624b\u5dfe\u3002 2.\u7528\u4e24\u4e2a\u624b\u6307\u626d\u4f4f\u76ae\u8089\u4f7f\u52b2\u8f6c\u52a8\uff1a\uff5e\u4ed6\u4e00\u4e0b\u3002 [n\u01d0ng]\uff1a1.\u626d\u8f6c\uff0c\u63a7\u5236\u4f4f\u4e1c\u897f\u7684\u4e00\u90e8\u5206\u800c\u7ede\u8f6c\uff1a\uff5e\u87ba\u4e1d\u9489\u3002 2.\u76f8\u53cd\uff0c\u4e0d\u987a\uff1a\u522b\u8ba9\u4ed6\u4fe9\u95f9\uff5e\u4e86\u3002 [n\u00ecng]\uff1a\u5014\u5f3a\uff0c\u522b\u626d\uff0c\u4e0d\u9a6f\u670d\uff1a\uff5e\u813e\u6c14\u3002\u72af\uff5e\u3002"],"line_type":["\u91d1"],"name":["\u62e7"],"pinyin":["n\u00edng","n\u01d0ng","n\u00ecng"],"sid":["49daaf73427711e59dc6c8e0eb15ce01"],"stroke_count":["8"],"type":["word"]},{"_id":31474061273,"_score":1,"_type":"vertex","_visited_num":1,"definition":["1.\u5c55\u5f00\uff0c\u4f38\u5c55\uff1a\uff5e\u5c55\u3002\uff5e\u7545\u3002\uff5e\u5f20\u3002\uff5e\u5377\uff08ju\u01cen\uff09\u3002\uff5e\u9002\u3002\uff5e\u5fc3\u3002 2.\u4ece\u5bb9\uff0c\u7f13\u6162\uff1a\uff5e\u7f13\u3002 3.\u59d3\u3002"],"line_type":["\u91d1"],"name":["\u8212"],"pinyin":["sh\u016b"],"radicals":["\u820c"],"sid":["5e9ead10a9eb44fd9e6cc57eafe07823"],"stroke_count":["12"],"type":["word"]},{"_id":32363254435,"_score":1,"_type":"vertex","_visited_num":1,"definition":["[zh\u0101n]\uff1a1.\u8ff7\u4fe1\u7684\u4eba\u7528\u94dc\u94b1\u6216\u7259\u724c\u7b49\u5224\u65ad\u5409\u51f6\uff1a\uff5e\u535c\u3002\uff5e\u5366\u3002 2.\u59d3\u3002 [zh\u00e0n]\uff1a1.\u636e\u6709\uff0c\u7528\u5f3a\u529b\u53d6\u5f97\uff1a\uff5e\u636e\u3002\u9738\uff5e\u3002\u5f3a\uff5e\u3002 2.\u5904\u4e8e\u67d0\u79cd\u5730\u4f4d\u6216\u60c5\u52bf\uff1a\uff5e\u7406\u3002\uff5e\u4f18\u52bf\u3002 3.\u53e3\u8bf4\uff0c\u53e3\u6388\u3002 4.\u4f30\u8ba1\u4e0a\u62a5\uff1a\u4ee4\u6c11\u5f97\u4ee5\u5f8b\uff5e\u79df\u3002"],"line_type":["\u91d1"],"name":["\u5360"],"pinyin":["zh\u0101n","zh\u00e0n"],"sid":["49c3d34a427711e5b238c8e0eb15ce01"],"stroke_count":["5"],"type":["word"]},{"_id":33369890022,"_score":1,"_type":"vertex","_visited_num":1,"definition":["\u53e4\u5f80\u4eca\u6765\u6240\u6709\u7684\u65f6\u95f4\uff1a\u5b87\uff5e\u3002"],"line_type":["\u91d1"],"name":["\u5b99"],"pinyin":["zh\u00f2u"],"radicals":["\u5b80"],"sid":["35e31b4f1e92405a855f67d8f9c0fd78"],"stroke_count":["8"],"type":["word"]},{"_id":32094815264,"_score":1,"_type":"vertex","_visited_num":1,"definition":["1.\u62b5\u3001\u9876\uff1a\u62b5\uff5e\u3002\u201c\u7f9d\u7f8a\uff5e\u85e9\uff0c\u8d62\u5176\u89d2\u201d\u3002 2.\u78b0\uff0c\u649e\uff1a\uff5e\u7901\u3002\uff5e\u7535\u3002\uff5e\u52a8\u3002\uff5e\u6478\u3002\uff5e\u53d1\u3002\uff5e\u72af\u3002\uff5e\u6012\u3002 3.\u9047\u7740\uff1a\u63a5\uff5e\u3002\uff5e\u89c9\uff08ju\u00e9\uff09\u3002\uff5e\u76ee\u60ca\u5fc3\u3002\uff5e\u89d2\uff08ji\u01ceo\uff09\u3002\uff5e\u666f\u751f\u60c5\u3002\uff5e\u7c7b\u65c1\u901a\u3002 4.\u56e0\u67d0\u79cd\u523a\u6fc0\u800c\u5f15\u8d77\u611f\u60c5\u53d8\u5316\uff1a\u611f\uff5e\u3002\u5ffd\u6709\u6240\uff5e\u3002"],"line_type":["\u91d1"],"name":["\u89e6"],"pinyin":["ch\u00f9"],"radicals":["\u89d2"],"sid":["6bd28a89748b420588fd0a572d54f31b"],"stroke_count":["13"],"type":["word"]},{"_id":30786192317,"_score":1,"_type":"vertex","_visited_num":1,"definition":["1.\u51fa\u4ee3\u4ef7\u6682\u7528\u522b\u4eba\u7684\u4e1c\u897f\uff1a\uff5e\u623f\u3002\uff5e\u7528\u3002\uff5e\u501f\u5730\u3002 2.\u6536\u53d6\u4e00\u5b9a\u7684\u4ee3\u4ef7\uff0c\u628a\u623f\u5c4b\u3001\u571f\u5730\u3001\u5668\u7269\u7b49\u501f\u7ed9\u522b\u4eba\u4f7f\u7528\uff1a\uff5e\u4f43\u3002\uff5e\u4ef7\u3002\uff5e\u8ba9\u3002\uff5e\u8d41\uff08\uff41\uff0e\u51fa\u79df\uff1b\uff42\uff0e\u79df\u7528\uff09\u3002 3.\u51fa\u79df\u6240\u6536\u53d6\u7684\u94b1\u6216\u5b9e\u7269\uff1a\u623f\uff5e\u3002\u5730\uff5e\u3002 4.\u7530\u8d4b\uff1a\uff5e\u7a0e\u3002"],"line_type":["\u91d1"],"name":["\u79df"],"pinyin":["z\u016b"],"radicals":["\u79be"],"sid":["1d73c67cfb524f9b896d293ece0cb26c"],"stroke_count":["10"],"type":["word"]},{"_id":32950462648,"_score":1,"_type":"vertex","_visited_num":1,"definition":["1.\u52a0\u5728\u95e8\u7a97\u3001\u5668\u7269\u7b49\u5f00\u5408\u5904\u6216\u8fde\u63a5\u5904\uff0c\u5fc5\u987b\u7528\u94a5\u5319\u3001\u5bc6\u7801\u3001\u78c1\u5361\u7b49\u624d\u80fd\u6253\u5f00\u7684\u91d1\u5c5e\u88c5\u7f6e\uff1a\u95e8\uff5e\u3002\u5bc6\u7801\uff5e\u3002\uff5e\u94a5\u3002 2.\u7528\u9501\u9501\u4f4f\uff1a\u628a\u95e8\uff5e\u4e0a\u3002 3.\u94fe\u5b50\uff1b\u94fe\u6761\uff1a\uff5e\u94fe\u3002\u67b7\uff5e\u3002\u957f\u547d\uff5e\u3002 4.\u5173\u95ed\uff1b\u5e7d\u95ed\uff1a\u95ed\u5173\uff5e\u56fd\u3002\u7ecf\u6d4e\u5c01\uff5e\u3002 5.\u7d27\u76b1\uff1b\u8e59\u7d27\uff1a\u6101\u7709\u6df1\uff5e\u3002 6.\u4e00\u79cd\u7f1d\u7eab\u65b9\u6cd5\uff0c\u7528\u7ebf\u987a\u7740\u5e03\u8fb9\u6216\u6263\u773c\u5bc6\u7f1d\uff1a\uff5e\u8fb9\u3002\uff5e\u6263\u773c\u3002 7.\u59d3\u3002"],"line_type":["\u91d1"],"name":["\u9501"],"pinyin":["su\u01d2"],"sid":["41bfba9196cc408793f8c9fdc41cb2bd"],"type":["word"]},{"_id":30853301379,"_score":1,"_type":"vertex","_visited_num":1,"definition":["\u7528\u5200\u522e\u53bb\u6bdb\u53d1\uff1a\uff5e\u5934\u3002\uff5e\u5200\u3002\uff5e\u5ea6\uff08\u4f5b\u6559\u6307\u7ed9\u8981\u51fa\u5bb6\u7684\u4eba\u5243\u53bb\u5934\u53d1\uff0c\u4f7f\u6210\u4e3a\u50e7\u5c3c\uff09\u3002"],"line_type":["\u91d1"],"name":["\u5243"],"pinyin":["t\u00ec"],"radicals":["\u5202"],"sid":["8e77b392c902454da89014e8be3ebb82"],"stroke_count":["9"],"type":["word"]},{"_id":31239180509,"_score":1,"_type":"vertex","_visited_num":1,"definition":["[q\u012b]\uff1a\u7537\u5b50\u7684\u914d\u5076\uff1a\uff5e\u5b50\u3002\uff5e\u5ba4\uff08\u6307\u59bb\u5b50\uff09\u3002\uff5e\u5c0f\uff08\u59bb\u5b50\u548c\u513f\u5973\uff09\u3002\uff5e\u79bb\u5b50\u6563\u3002 [q\u00ec]\uff1a\u4ee5\u5973\u5ac1\u4eba\u3002"],"line_type":["\u91d1"],"name":["\u59bb"],"pinyin":["q\u012b","q\u00ec"],"radicals":["\u5973"],"sid":["1fe230ee90e2419e80c0baa74bcdf2e7"],"stroke_count":["8"],"type":["word"]},{"_id":33621541826,"_score":1,"_type":"vertex","_visited_num":1,"definition":["1.\u50cf\u918b\u7684\u6c14\u5473\u6216\u5473\u9053\uff1a\uff5e\u83dc\u3002\uff5e\u6e9c\u6e9c\u3002\uff5e\u6885\u3002\uff5e\u751c\u3002\uff5e\u5976\u3002\uff5e\u67a3\u3002 2.\u5316\u5b66\u4e0a\u79f0\u80fd\u5728\u6c34\u6eb6\u6db2\u4e2d\u4ea7\u751f\u6c22\u79bb\u5b50\u7684\u5316\u5408\u7269\uff0c\u5206\u201c\u65e0\u673a\u9178\u201d\u3001\u201c\u6709\u673a\u9178\u201d\u4e24\u5927\u7c7b\uff1a\u76d0\uff5e\u3002\u78b3\uff5e\u3002\u785d\uff5e\u3002\u786b\uff5e\u3002\uff5e\u78b1\u5ea6\u3002 3.\u8ba5\u8bbd\u4eba\u7684\u8fc2\u8150\uff1a\u7a77\uff5e\u3002\u5bd2\uff5e\u3002 4.\u60b2\u75db\uff0c\u4f24\u5fc3\uff1a\uff5e\u695a\u3002\u8f9b\uff5e\uff08\u4ea6\u4f5c\u201c\u9178\u8f9b\u201d\uff09\u3002\uff5e\u82e6\u3002\uff5e\u6006\u3002\uff5e\u6000\u3002 5.\u56e0\u75b2\u52b3\u6216\u75be\u75c5\u5f15\u8d77\u7684\u5fae\u75db\u800c\u65e0\u529b\u7684\u611f\u89c9\uff1a\uff5e\u75db\u3002\u8170\uff5e\u817f\u75bc\u3002"],"line_type":["\u91d1"],"name":["\u9178"],"pinyin":["su\u0101n"],"radicals":["\u9149"],"sid":["4ad570c8051344d98376180d5d7c45c4"],"stroke_count":["14"],"type":["word"]},{"_id":30366765774,"_score":1,"_type":"vertex","_visited_num":1,"definition":["[s\u00f9]\uff1a1.\u4f4f\uff0c\u8fc7\u591c\uff0c\u591c\u91cc\u7761\u89c9\uff1a\u4f4f\uff5e\u3002\u7559\uff5e\u3002\u9732\uff5e\u3002\uff5e\u820d\uff08sh\u00e8\uff09\u3002\uff5e\u8425\u3002 2.\u5e74\u8001\u7684\uff0c\u957f\u4e45\u4ece\u4e8b\u67d0\u79cd\u5de5\u4f5c\u7684\uff1a\uff5e\u5c06\uff08\u7ecf\u9a8c\u4e30\u5bcc\u7684\u8001\u5c06\uff09\u3002\uff5e\u5112\u3002\u540d\uff5e\u3002 3.\u5e73\u7d20\uff0c\u7d20\u6709\u7684\uff1a\uff5e\u613f\u3002\uff5e\u5fd7\u3002\uff5e\u75be\u3002\uff5e\u654c\u3002\uff5e\u5fc3\u3002 4.\u9694\u591c\u7684\uff0c\u9694\u5e74\u7684\uff1a\uff5e\u96e8\uff08\u6628\u591c\u7684\u96e8\uff09\u3002\uff5e\u6839\u3002\uff5e\u8349\u3002 5.\u59d3\u3002 [xi\u01d4]\uff1a\u591c\uff1a\u4e00\uff5e\u3002\u4e24\uff5e\u3002 [xi\u00f9]\uff1a\u661f\u5ea7\uff1a\u661f\uff5e\u3002"],"line_type":["\u91d1"],"name":["\u5bbf"],"pinyin":["s\u00f9","xi\u01d4","xi\u00f9"],"sid":["49d1144f427711e580eec8e0eb15ce01"],"stroke_count":["11"],"type":["word"]},{"_id":33235669752,"_score":1,"_type":"vertex","_visited_num":1,"definition":["[g\u0101ng]\uff1a\u7ecf\u8fc7\u7cbe\u70bc\uff0c\u4e0d\u542b\u78f7\u7802\u7b49\u6742\u8d28\u7684\u94c1\uff0c\u542b\u78b30.15\uff5e1.7\uff05\uff0c\u6bd4\u719f\u94c1\u66f4\u575a\u786c\u66f4\u5bcc\u4e8e\u5f39\u6027\uff0c\u662f\u5de5\u4e1a\u4e0a\u6781\u5176\u91cd\u8981\u7684\u539f\u6599\uff1a\uff5e\u677f\u3002\uff5e\u7b14\uff08\u7b14\u5934\u7528\u91d1\u5c5e\u5236\u6210\u7684\u7b14\uff09\u3002\uff5e\u94c1\uff08\u201c\u94a2\u201d\u548c\u201c\u94c1\u201d\uff0c\u55bb\u575a\u5f3a\uff0c\u5982\u201c\uff5e\uff5e\u7684\u610f\u5fd7\u201d\uff09\u3002\u8f67\uff5e\u3002 [g\u00e0ng]\uff1a1.\u628a\u5200\u5728\u5e03\u3001\u76ae\u3001\u77f3\u3001\u6216\u7f38\u6cbf\u4e0a\u7528\u529b\u6469\u64e6\u51e0\u4e0b\uff0c\u4f7f\u950b\u5229\u4e9b\uff1a\u628a\u5200\uff5e\u4e00\uff5e\u3002 2.\u5728\u5200\u53e3\u4e0a\u52a0\u70b9\u513f\u94a2\uff08g\u0101ng\uff09\uff0c\u91cd\u65b0\u6253\u9020\uff0c\u4f7f\u66f4\u950b\u5229\uff1a\u8fd9\u53e3\u94e1\u5200\u8be5\uff5e\u4e86\u3002"],"line_type":["\u91d1"],"name":["\u94a2"],"pinyin":["g\u0101ng","g\u00e0ng"],"sid":["4a05ca85427711e5a011c8e0eb15ce01"],"stroke_count":["9"],"type":["word"]},{"_id":31222402431,"_score":1,"_type":"vertex","_visited_num":1,"definition":["1.\u53bb\u6389\u963b\u585e\u4f7f\u901a\u7545\uff1a\uff5e\u5bfc\u3002\uff5e\u901a\u3002\uff5e\u6d5a\u3002\uff5e\u89e3\uff08ji\u011b\uff09\u3002 2.\u5206\u6563\uff1a\uff5e\u6563\u3002\u4ed7\u4e49\uff5e\u8d22\u3002 3.\u4e8b\u7269\u95f4\u8ddd\u79bb\u5927\uff0c\u7a7a\u9699\u5927\uff0c\u4e0e\u201c\u5bc6\u201d\u76f8\u5bf9\uff1a\uff5e\u5bc6\u3002\uff5e\u677e\u3002\uff5e\u6717\u3002\uff5e\u65f7\u3002\uff5e\u9614\u3002\uff5e\u843d\uff08lu\u00f2\uff09\u3002\u7a00\uff5e\u3002\u5929\u7f51\u6062\u6062\uff0c\uff5e\u800c\u4e0d\u6f0f\u3002 4.\u4e0d\u4eb2\u5bc6\uff0c\u5173\u7cfb\u8fdc\u7684\uff1a\u4eb2\uff5e\u3002\uff5e\u8fdc\u3002 5.\u4e0d\u7ec6\u5bc6\uff0c\u5ffd\u7565\uff1a\uff5e\u5ffd\u3002 6.\u7a7a\u865a\uff1a\u5fd7\u5927\u624d\uff5e\u3002 7.\u4e0d\u719f\u6089\uff1a\u751f\uff5e\u3002 8.\u7c97\u52a3\uff1a\uff5e\u98df\u3002\uff5e\u7c9d\u3002 9.\u53e4\u540c\u201c\u852c\u201d\uff0c\u852c\u83dc\u3002 10.\u5206\u6761\u8bf4\u660e\u7684\u6587\u5b57\uff1a\u4e0a\uff5e\uff08\u81e3\u5b50\u5411\u5e1d\u738b\u5206\u6761\u9648\u8ff0\u7684\u610f\u89c1\u4e66\uff09\u3002\u594f\uff5e\u3002\u6ce8\uff5e\uff08\u5bf9\u53e4\u4e66\u7684\u6ce8\u89e3\u548c\u5bf9\u6ce8\u89e3\u7684\u6ce8\u91ca\uff09\u3002 11.\u50e7\u9053\u62dc\u5fcf\u65f6\u6240\u711a\u5316\u7684\u795d\u544a\u6587\u3002 12.\u59d3\u3002"],"line_type":["\u91d1"],"name":["\u758f"],"pinyin":["sh\u016b"],"radicals":["\u758b"],"sid":["289f825154084e9788af883de23b42ce"],"stroke_count":["12"],"type":["word"]},{"_id":33772536852,"_score":1,"_type":"vertex","_visited_num":1,"definition":["1.\u8fd1\u8eab\u8863\uff0c\u5185\u8863\uff1a\uff5e\u886b\u3002\uff5e\u88e4\u3002 2.\u5728\u91cc\u9762\u518d\u6258\u4e0a\u4e00\u5c42\uff1a\uff5e\u7ed2\u3002\uff5e\u780c\u3002 3.\u642d\u914d\u4e0a\u522b\u7684\u4e1c\u897f\uff1a\uff5e\u6258\u3002\u966a\uff5e\u3002\u6620\uff5e\u3002 4.\u9644\u5728\u8863\u88f3\u67d0\u4e00\u90e8\u5206\u91cc\u9762\u7684\u7eba\u7ec7\u54c1\uff1a\u9886\uff5e\u513f\u3002\u8896\uff5e\u513f\u3002"],"line_type":["\u91d1"],"name":["\u886c"],"pinyin":["ch\u00e8n"],"radicals":["\u8864"],"sid":["9265c86579f544a7abc1446fe4a60c24"],"stroke_count":["8"],"type":["word"]},{"_id":31574729256,"_score":1,"_type":"vertex","_visited_num":1,"definition":["1.\u5fc5\u5f97\u7528\uff1a\uff5e\u6c42\u3002\uff5e\u8981\u3002\u5fc5\uff5e\u3002\u6025\uff5e\u3002 2.\u5fc5\u5f97\u7528\u7684\u8d22\u7269\uff1a\u519b\uff5e\u3002\u6c11\uff5e\u3002 3.\u7b49\u5f85\u3002 4.\u8fdf\u7591\u3002"],"line_type":["\u91d1"],"name":["\u9700"],"pinyin":["x\u016b"],"radicals":["\u96e8"],"sid":["2c744f2b045b4e7cbc8edd45af29a23b"],"stroke_count":["14"],"type":["word"]},{"_id":32245817504,"_score":1,"_type":"vertex","_visited_num":1,"definition":["\u6025\u4fc3\u5730\u547c\u5438\uff1a\uff5e\u6c14\u3002\uff5e\u606f\u3002\uff5e\u54b3\u3002\u82df\u5ef6\u6b8b\uff5e\u3002"],"line_type":["\u91d1"],"name":["\u5598"],"pinyin":["chu\u01cen"],"radicals":["\u53e3"],"sid":["a506562e6cb84db5b00f4c67464559fb"],"stroke_count":["12"],"type":["word"]},{"_id":30115112626,"_score":1,"_type":"vertex","_visited_num":1,"definition":["1.\u4eba\u6216\u52a8\u7269\u751f\u5b50\uff1a\uff5e\u5b50\u3002\uff5e\u5375\u3002\uff5e\u5987\u3002\u52a9\uff5e\u58eb\u3002 2.\u5236\u9020\uff0c\u517b\u79cd\u690d\u6216\u81ea\u7136\u751f\u957f\uff1a\u5de5\u4e1a\u751f\uff5e\u3002\uff5e\u503c\u3002 3.\u5236\u9020\u3001\u517b\u3001\u79cd\u690d\u6216\u81ea\u7136\u751f\u957f\u7684\u4e1c\u897f\uff1a\u571f\uff5e\u3002\u7279\uff5e\u3002 4.\u751f\u51fa\uff0c\u51fa\u73b0\uff1a\uff5e\u751f\u3002\u51fa\uff5e\u3002\uff5e\u5730\u3002 5.\u8d22\u7269\uff1a\u8d22\uff5e\u3002\u9057\uff5e\u3002\uff5e\u6743\u3002"],"line_type":["\u91d1"],"name":["\u4ea7"],"pinyin":["ch\u01cen"],"radicals":["\u4ea0"],"sid":["7534c0d943fa41b28cc7c05db3adb226"],"stroke_count":["6"],"type":["word"]},{"_id":30232548040,"_score":1,"_type":"vertex","_visited_num":1,"definition":["[c\u00e8]\uff1a1.\u65c1\uff1a\uff5e\u9762\u3002\uff5e\u5f71\u3002\uff5e\u95e8\u3002\uff5e\u5ba4\u3002\uff5e\u7ffc\u3002\uff5e\u8bb0\uff08\u5173\u4e8e\u67d0\u4e9b\u6d3b\u52a8\u7684\u4fa7\u9762\u7684\u62a5\u9053\uff09\u3002 2.\u659c\u7740\uff1a\uff5e\u91cd\uff08zh\u00f2ng\uff09\uff08\u504f\u91cd\uff09\u3002\uff5e\u5c04\u3002\uff5e\u5367\u3002\uff5e\u679d\u3002\uff5e\u82bd\u3002\u8f97\u8f6c\u53cd\uff5e\u3002 3.\u5351\u964b\uff1a\uff5e\u964b\uff08a.\u504f\u50fb\u7b80\u964b\uff1bb.\u6307\u5730\u4f4d\u4f4e\u4e0b\uff09\u3002 [z\u00e8]\uff1a\u540c\u201c\u4ec4\u201d\u3002 [zh\u0101i]\uff1a1.\u3014\uff5e\u6b6a\u3015\u503e\u659c\uff0c\u5982\u201c\u4f60\u770b\u90a3\u4eba\uff5e\uff5e\u7740\u8d70\u201d\u3002 2.\uff08\u5074\uff09"],"line_type":["\u91d1"],"name":["\u4fa7"],"pinyin":["c\u00e8","z\u00e8","zh\u0101i"],"sid":["49bdc6c0427711e5a6bbc8e0eb15ce01"],"stroke_count":["8"],"type":["word"]},{"_id":33000795198,"_score":1,"_type":"vertex","_visited_num":1,"definition":["1.\u7c73\u8131\u58f3\u800c\u672a\u8202\u7684\u72b6\u6001\uff1a\uff5e\u7c73\u3002 2.\u4e0d\u7ec6\u81f4\uff0c\u4e0d\u5149\u6ed1\uff1a\u7c97\uff5e\u3002\u6bdb\uff5e\u3002"],"line_type":["\u91d1"],"name":["\u7cd9"],"pinyin":["c\u0101o"],"radicals":["\u7c73"],"sid":["649a26b737b24c0db722761ab1df9c2c"],"stroke_count":["16"],"type":["word"]}],"ret_type":"multiword","hilight":{"radicals":"all","strokes":"all","line_type":"\u91d1"},"page_total":76,"tag":{"tagLists":{"radicals":["\u5168\u90e8","\u6c35<span>(\u5e38\u89c1)<\/span>","\u6728","\u8279","\u53e3","\u624c","\u9485","\u4ebb","\u5973","\u866b","\u571f","\u8ba0","\u5fc4","\u706b","\u7e9f","\u7af9","\u5c71","\u6708","\u961d","\u77f3","\u4e00<span>(1\u753b)<\/span>","\u4e3f","\u4e59","\u4e28","\u4e5a","\u4e36","\u4e85","\u5202<span>(2\u753b)<\/span>","\u529b","\u51ab","\u5382","\u531a","\u4eba","\u4ea0","\u5341","\u5200","\u52f9","\u53c8","\u5196","\u5182","\u516b","\u513f","\u4e8c","\u5369","\u53b6","\u51e0","\u51f5","\u4e37","\u5ef4","\u535c","\u5165","\u5315","\u5338","\u8fb6<span>(3\u753b)<\/span>","\u72ad","\u5b80","\u5e7f","\u5dfe","\u5f73","\u5927","\u56d7","\u9a6c","\u5f13","\u5c38","\u9963","\u95e8","\u5b50","\u58eb","\u5bf8","\u5915","\u5c0f","\u5f61","\u5902","\u5c22","\u5efe","\u5de5","\u5df3","\u5f0b","\u5f50","\u5e72","\u5f51","\u5ddb","\u5e7a","\u5df1","\u5140","\u98de","\u5ddd","\u5c6e","\u738b<span>(4\u753b)<\/span>","\u65e5","\u5fc3","\u793b","\u8d1d","\u6b20","\u6535","\u725c","\u6b79","\u6bdb","\u8f66","\u74e6","\u6208","\u6c34","\u624b","\u706c","\u65b9","\u6c14","\u6bb3","\u6b62","\u66f0","\u65a4","\u6237","\u725b","\u72ac","\u89c1","\u6534","\u7247","\u6587","\u6597","\u98ce","\u8002","\u723f","\u722b","\u6bd4","\u97e6","\u722a","\u6c0f","\u652f","\u5384","\u7236","\u6bcb","\u65e1","\u723b","\u5c23","\u7259","\u8080","\u535d","\u957f","\u76ee<span>(5\u753b)<\/span>","\u9485","\u7592","\u8864","\u79be","\u7530","\u7a74","\u9e1f","\u76bf","\u7f52","\u7acb","\u767d","\u793a","\u76ae","\u77e2","\u7389","\u74dc","\u751f","\u7528","\u7518","\u758b","\u77db","\u7676","\u6bcd","\u7384","\u9f99","\u4e1a","\u6b7a","\u7c73<span>(6\u753b)<\/span>","\u821f","\u8033","\u7fbd","\u8863","\u9875","\u7cf9","\u7cf8","\u7f8a","\u8012","\u864d","\u7f36","\u884c","\u81fc","\u820c","\u8840","\u8089","\u8980","\u81ea","\u81f3","\u807f","\u81e3","\u8272","\u800c","\u826e","\u8278","\u7f51","\u9f50","\u5148","\u897f","\u8a00<span>(7\u753b)<\/span>","\u8db3","\u8eca","\u8c9d","\u9149","\u8d70","\u898b","\u89d2","\u8c78","\u8c55","\u8eab","\u8f9b","\u8c46","\u8c37","\u8d64","\u9091","\u9578","\u514b","\u8fb0","\u91cc","\u9ea6","\u5364","\u8fb5","\u91d2<span>(8\u753b)<\/span>","\u98e0","\u96e8","\u9c7c","\u9580","\u96b9","\u91d1","\u9f7f","\u9752","\u91c7","\u975e","\u96b6","\u9577","\u961c","\u9763","\u9751","\u9801<span>(9\u753b)<\/span>","\u9769","\u9aa8","\u98a8","\u9b3c","\u97cb","\u9999","\u97f3","\u9762","\u97ed","\u9996","\u98df","\u99ac<span>(10\u753b)<\/span>","\u9adf","\u9b25","\u9b32","\u9ad8","\u9b2f","\u9ce5<span>(11\u753b)<\/span>","\u9b5a","\u9e7f","\u9ea5","\u9ec4","\u9e75","\u9ebb","\u9ed1<span>(12\u753b)<\/span>","\u9efd","\u9f0e","\u9ef9","\u9ecd","\u9f20<span>(\u66f4\u591a)<\/span>","\u9f13","\u9f3b","\u9f4a","\u9f52","\u9f8d","\u9fa0"],"strokes":["\u5168\u90e8","1\u753b","2\u753b","3\u753b","4\u753b","5\u753b","6\u753b","7\u753b","8\u753b","9\u753b","10\u753b","11\u753b","12\u753b","13\u753b","14\u753b","15\u753b","16\u753b","17\u753b","18\u753b","19\u753b","20\u753b","21\u753b","22\u753b","23\u753b","24\u753b","25\u753b","26\u753b","27\u753b","28\u753b","29\u753b","30\u753b","31\u753b","32\u753b","33\u753b","34\u753b","35\u753b","36\u753b","37\u753b","38\u753b","39\u753b","40\u753b","41\u753b","42\u753b","43\u753b","44\u753b","45\u753b","46\u753b","47\u753b","48\u753b"],"line_type":["\u5168\u90e8","\u91d1","\u6728","\u6c34","\u706b","\u571f"]},"nameMapping":{"radicals":"\u90e8\u9996","strokes":"\u7b14\u753b","line_type":"\u4e94\u884c"},"activeTags":{"radicals":["\u5168\u90e8"],"strokes":["\u5168\u90e8"],"line_type":["\u91d1"]}},"result_type":"zici"}