{"ret_num":1503,"ret_array":[{"_id":33738994645,"_score":1,"_type":"vertex","_visited_num":1,"definition":["1.\u611a\u6627\uff1a\uff5e\u8499\uff08\u611a\u6627\u65e0\u77e5\uff09\u3002 2.\u5584\u826f\uff1a\uff5e\u6c11\uff08\u5584\u826f\u7684\u767e\u59d3\uff09\u3002 3.\u3014\uff5e\u987c\u3015\u4f20\u8bf4\u4e2d\u7684\u4e0a\u53e4\u5e1d\u738b\u3002 4.\u540c\u201c\u4e13\u201d\u3002"],"line_type":["\u91d1"],"name":["\u989b"],"pinyin":["zhu\u0101n"],"radicals":["\u9875"],"sid":["ebe42d3533834c41b5c23a3df4d5fcf4"],"stroke_count":["15"],"type":["word"]},{"_id":30417094312,"_score":1,"_type":"vertex","_visited_num":1,"definition":["\u7559\u4f4f\u3002\u843d\u811a\u3002"],"line_type":["\u91d1"],"name":["\u50ba"],"pinyin":["ch\u00ec"],"radicals":["\u4ebb"],"sid":["dccd23e62c37419ca007a028b22e2e63"],"stroke_count":["13"],"type":["word"]},{"_id":34342962010,"_score":1,"_type":"vertex","_visited_num":1,"definition":["1.\u53e4\u4ee3\u5175\u5668\uff0c\u9752\u94dc\u5236\uff0c\u50cf\u65a7\uff0c\u6bd4\u65a7\u5927\uff0c\u5706\u5203\u53ef\u780d\u5288\uff0c\u4e2d\u56fd\u5546\u53ca\u897f\u5468\u76db\u884c\u3002\u53c8\u6709\u7389\u77f3\u5236\u7684\uff0c\u4f9b\u793c\u4eea\u3001\u6ba1\u846c\u7528\u3002 2.\u53e4\u661f\u540d\u3002"],"line_type":["\u91d1"],"name":["\u94ba"],"pinyin":["yu\u00e8"],"radicals":["\u9485"],"sid":["f46b0ec12a14467883dbbd2594e0ba45"],"stroke_count":["10"],"type":["word"]},{"_id":34074527761,"_score":1,"_type":"vertex","_visited_num":1,"definition":["1.\u3014\uff5e\u9c7c\u3015\u4f53\u4fa7\u6241\uff0c\u5f62\u7565\u4f3c\u9c91\u9c7c\uff0c\u5168\u8eab\u6709\u663e\u8457\u7684\u9ed1\u70b9\u3002\u5e38\u6816\u6d77\u4e2d\uff0c\u590f\u5b63\u4e0a\u6eaf\u4e8e\u6cb3\u4ea7\u5375\uff0c\u79cb\u672b\u53c8\u5165\u6d77\u3002\u8089\u53ef\u98df\uff0c\u4e3a\u517b\u6b96\u7684\u540d\u8d35\u9c7c\u79cd\u3002 2.\uff08\u9c52\uff09"],"line_type":["\u91d1"],"name":["\u9cdf"],"pinyin":["z\u016bn"],"radicals":["\u9c7c"],"sid":["f8e75b37a9d14e7f81828b1700994b56"],"stroke_count":["20"],"type":["word"]},{"_id":32614912533,"_score":1,"_type":"vertex","_visited_num":1,"definition":["\u3014\u5541\uff08zh\u0101o\uff09\uff5e\u3015\u89c1\u201c\u55412\u201d\u3002"],"line_type":["\u91d1"],"name":["\u54f3"],"pinyin":["zh\u0101"],"radicals":["\u53e3"],"sid":["fa1b3e0b552844f38f920b8a371133d0"],"stroke_count":["10"],"type":["word"]},{"_id":34175189750,"_score":1,"_type":"vertex","_visited_num":1,"definition":["1.\u53e4\u540c\u201c\u8be7\u201d\uff0c\u5938\u8000\u81ea\u5df1\u3002 2.\u3014\uff5e\u50ba\uff08ch\u00ec\uff09\u3015\u5931\u610f\u3002"],"line_type":["\u91d1"],"name":["\u4f98"],"pinyin":["ch\u00e0"],"radicals":["\u4ebb"],"sid":["def45b7cce514b9f96c78de027bdb5f1"],"stroke_count":["8"],"type":["word"]},{"_id":30417101666,"_score":1,"_type":"vertex","_visited_num":1,"definition":["\u4e00\u79cd\u91d1\u5c5e\u5143\u7d20\uff0c\u7070\u767d\u8272\u7ed3\u6676\uff0c\u8d28\u8106\uff0c\u662f\u91cd\u8981\u7684\u534a\u5bfc\u4f53\u6750\u6599\u3002"],"line_type":["\u91d1"],"name":["\u9517"],"pinyin":["zh\u011b"],"radicals":["\u9485"],"sid":["0394d55bb8d34142a5dfe5131ebc02d1"],"stroke_count":["13"],"type":["word"]},{"_id":30601642941,"_score":1,"_type":"vertex","_visited_num":1,"definition":["[t\u0101]\uff1a\u4e00\u79cd\u91d1\u5c5e\u5143\u7d20\uff0c\u7528\u6765\u5236\u9020\u5149\u7535\u7ba1\uff0c\u4f4e\u6e29\u6e29\u5ea6\u8ba1\uff0c\u5149\u5b66\u73bb\u7483\u7b49\u3002\u5b83\u7684\u76d0\u7c7b\u6709\u6bd2\uff0c\u7528\u4e8e\u533b\u836f\u3002 [tu\u00f3]\uff1a\u540c\u201c\u7823\u201d\u3002"],"line_type":["\u91d1"],"name":["\u94ca"],"pinyin":["t\u0101","tu\u00f3"],"radicals":["\u9485"],"sid":["2254ca64696d4e8fa040b6fd9a7d2b47"],"stroke_count":["10"],"type":["word"]},{"_id":32396806224,"_score":1,"_type":"vertex","_visited_num":1,"definition":["[c\u01ceo]\uff1a\u3014\uff5e\uff5e\u3015\u5fe7\u8651\u4e0d\u5b89\u3002 [s\u0101o]\uff1a\u53e4\u540c\u201c\u6145\u201d\uff0c\u9a9a\u52a8\u3002 [s\u00e0o]\uff1a\u8d2a\u56fe\u3002"],"line_type":["\u91d1"],"name":["\u61c6"],"pinyin":["c\u01ceo","s\u0101o","s\u00e0o"],"radicals":["\u5fc4"],"sid":["0ecb392d532e4839bfdd9165b530747a"],"stroke_count":["16"],"type":["word"]},{"_id":33973863352,"_score":1,"_type":"vertex","_visited_num":1,"definition":["1.\u53e4\u4ee3\u6307\u8f66\u6bc2\u5916\u7aef\u7684\u5c0f\u5b54\u3002 2.\u8f66\u8f74\u7aef\uff0c\u8f74\u5934\u3002"],"line_type":["\u91d1"],"name":["\u8f75"],"pinyin":["zh\u01d0"],"radicals":["\u8f66"],"sid":["3bf8985e1b694556bb06dc70c1b4f6bc"],"stroke_count":["9"],"type":["word"]},{"_id":31910266956,"_score":1,"_type":"vertex","_visited_num":1,"definition":["1.\u51b5\u4e14\u3002 2.\u4ea6\u3002"],"line_type":["\u91d1"],"name":["\u77e7"],"pinyin":["sh\u011bn"],"radicals":["\u77e2"],"sid":["0917c27c061c45839eba687dd3964b87"],"stroke_count":["9"],"type":["word"]},{"_id":32145155057,"_score":1,"_type":"vertex","_visited_num":1,"definition":["\u3014\uff5e\u8788\u3015\u4e24\u6816\u52a8\u7269\uff0c\u5f62\u72b6\u4f3c\u8725\u8734\u3002\u5934\u6241\u5e73\uff0c\u56db\u80a2\u7ec6\u957f\uff0c\u65e0\u8e7c\uff0c\u5c3e\u4fa7\u6241\uff0c\u5375\u751f\u3002\u751f\u6d3b\u4e8e\u6e05\u51b7\u7684\u6c60\u6cbc\u5185\uff0c\u4ea6\u89c1\u4e8e\u6e7f\u5730\u7684\u8349\u4e1b\u4e2d\u3002"],"line_type":["\u91d1"],"name":["\u877e"],"pinyin":["r\u00f3ng"],"radicals":["\u866b"],"sid":["38af1aef714a4eb0a05077eceabd5e89"],"stroke_count":["15"],"type":["word"]},{"_id":30467425705,"_score":1,"_type":"vertex","_visited_num":1,"definition":["\u6709\u673a\u5316\u5408\u7269\u8bd1\u97f3\u5b57\u3002"],"line_type":["\u91d1"],"name":["\u5511"],"pinyin":["zu\u00f2"],"radicals":["\u53e3"],"sid":["02d846b97d694758a61f25c56808e728"],"stroke_count":["10"],"type":["word"]},{"_id":30517760236,"_score":1,"_type":"vertex","_visited_num":1,"definition":["[ch\u014du]\uff1a1.\u62bd\u5f15\uff0c\u7406\u51fa\u4e1d\u7f15\u7684\u5934\u7eea\u3002 2.\u7f00\u96c6\uff1a\u201c\u8fc1\u4e3a\u592a\u53f2\u4ee4\uff0c\uff5e\u53f2\u8bb0\u77f3\u5ba4\u91d1\u532e\u4e4b\u4e66\u3002\u201d [ch\u00f3u]\uff1a\u53e4\u540c\u201c\u7ef8\u201d\u3002"],"line_type":["\u91d1"],"name":["\u7d2c"],"pinyin":["ch\u014du","ch\u00f3u"],"radicals":["\u7cf9"],"sid":["0d9d99d075a741d39e7ccf7359fac71b"],"stroke_count":["11"],"type":["word"]},{"_id":31943819674,"_score":1,"_type":"vertex","_visited_num":1,"definition":["\u3014\uff5e\u8e14\uff08chu\u014d\uff09\u3015\uff41\uff0e\u4e00\u811a\u8df3\u884c\u3001\u8ddb\u811a\u8d70\u8def\u7684\u6837\u5b50\uff1b\uff42\uff0e\u8fc5\u901f\u6ecb\u957f\uff1b\uff43\uff0e\u5954\u8dc3\u3002"],"line_type":["\u91d1"],"name":["\u8e38"],"pinyin":["ch\u011bn"],"radicals":["\u8db3"],"sid":["34955340d91d48cfb89ed51a5aca2f8d"],"stroke_count":["16"],"type":["word"]},{"_id":33269228683,"_score":1,"_type":"vertex","_visited_num":1,"definition":["\u4e00\u79cd\u91d1\u5c5e\u5143\u7d20\uff0c\u7b26\u53f7Cr\uff0c\u8d28\u786c\u800c\u8106\uff0c\u6297\u8150\u8680\u6027\u5f3a\u3002\u7528\u4e8e\u7535\u9540\u548c\u5236\u9020\u7279\u79cd\u94a2\u3002"],"line_type":["\u91d1"],"name":["\u94ec"],"pinyin":["g\u00e8"],"radicals":["\u9485"],"sid":["3cf6d4e124104b1d8c44626500bb082f"],"stroke_count":["11"],"type":["word"]},{"_id":30517763768,"_score":1,"_type":"vertex","_visited_num":1,"definition":["\u53e4\u540c\u201c\u81ed\u201d\uff0c\u8150\u81ed\u6c14\u5473\uff1a\u201c\u6614\u5e1d\u5c27\u4e4b\u846c\u4e5f\u2026\u2026\u5176\u7a7f\u4e0b\u4e0d\u4e71\u6cc9\uff0c\u4e0a\u4e0d\u6cc4\uff5e\u3002\u201d"],"line_type":["\u91d1"],"name":["\u6ba0"],"pinyin":["ch\u00f2u"],"radicals":["\u6b79"],"sid":["297f25f5b6474252ab949b02c5d8336f"],"stroke_count":["14"],"type":["word"]},{"_id":33101457922,"_score":1,"_type":"vertex","_visited_num":1,"definition":["1.\u3014\uff5e\u4948\u3015\u5c0f\u9505\u3002 2.\u5316\u5b66\u5143\u7d20\u201c\u922e\u201d\u7684\u65e7\u8bd1\u3002"],"line_type":["\u91d1"],"name":["\u94b6"],"pinyin":["k\u0113"],"radicals":["\u9485"],"sid":["2c19d4bbfb484d249adfd6fc6507538d"],"stroke_count":["10"],"type":["word"]},{"_id":31121738050,"_score":1,"_type":"vertex","_visited_num":1,"definition":["1.\u8863\u895f\uff1a\u201c\u8fde\uff5e\u6210\u5e37\u201d\u3002\u655b\uff5e\u3002 2.\u8863\u8896\u3002 3.\u53e4\u4ee3\u7761\u89c9\u65f6\u7528\u7684\u5e2d\u5b50\uff1a\uff5e\u5e2d\u3002"],"line_type":["\u91d1"],"name":["\u887d"],"pinyin":["r\u00e8n"],"radicals":["\u8864"],"sid":["26ce47b98fb444928c3dfae42e86147a"],"stroke_count":["9"],"type":["word"]},{"_id":33336340041,"_score":1,"_type":"vertex","_visited_num":1,"definition":["[ch\u01cen]\uff1a1.\u5bbd\u677e\u7684\u4e1d\u5e26\u3002 2.\u8212\u7f13\uff1b\u5766\u7136\u3002 [ch\u00e1n]\uff1a\u3014\uff5e\u8054\u3015\u8fde\u7ef5\u4e0d\u65ad\u7684\u6837\u5b50\u3002"],"line_type":["\u91d1"],"name":["\u7e5f"],"pinyin":["ch\u01cen","ch\u00e1n"],"radicals":["\u7cf9"],"sid":["28fe7010c3de44979a8c9c201d597b8d"],"stroke_count":["18"],"type":["word"]}],"ret_type":"multiword","hilight":{"radicals":"all","strokes":"all","line_type":"\u91d1"},"page_total":76,"tag":{"tagLists":{"radicals":["\u5168\u90e8","\u6c35<span>(\u5e38\u89c1)<\/span>","\u6728","\u8279","\u53e3","\u624c","\u9485","\u4ebb","\u5973","\u866b","\u571f","\u8ba0","\u5fc4","\u706b","\u7e9f","\u7af9","\u5c71","\u6708","\u961d","\u77f3","\u4e00<span>(1\u753b)<\/span>","\u4e3f","\u4e59","\u4e28","\u4e5a","\u4e36","\u4e85","\u5202<span>(2\u753b)<\/span>","\u529b","\u51ab","\u5382","\u531a","\u4eba","\u4ea0","\u5341","\u5200","\u52f9","\u53c8","\u5196","\u5182","\u516b","\u513f","\u4e8c","\u5369","\u53b6","\u51e0","\u51f5","\u4e37","\u5ef4","\u535c","\u5165","\u5315","\u5338","\u8fb6<span>(3\u753b)<\/span>","\u72ad","\u5b80","\u5e7f","\u5dfe","\u5f73","\u5927","\u56d7","\u9a6c","\u5f13","\u5c38","\u9963","\u95e8","\u5b50","\u58eb","\u5bf8","\u5915","\u5c0f","\u5f61","\u5902","\u5c22","\u5efe","\u5de5","\u5df3","\u5f0b","\u5f50","\u5e72","\u5f51","\u5ddb","\u5e7a","\u5df1","\u5140","\u98de","\u5ddd","\u5c6e","\u738b<span>(4\u753b)<\/span>","\u65e5","\u5fc3","\u793b","\u8d1d","\u6b20","\u6535","\u725c","\u6b79","\u6bdb","\u8f66","\u74e6","\u6208","\u6c34","\u624b","\u706c","\u65b9","\u6c14","\u6bb3","\u6b62","\u66f0","\u65a4","\u6237","\u725b","\u72ac","\u89c1","\u6534","\u7247","\u6587","\u6597","\u98ce","\u8002","\u723f","\u722b","\u6bd4","\u97e6","\u722a","\u6c0f","\u652f","\u5384","\u7236","\u6bcb","\u65e1","\u723b","\u5c23","\u7259","\u8080","\u535d","\u957f","\u76ee<span>(5\u753b)<\/span>","\u9485","\u7592","\u8864","\u79be","\u7530","\u7a74","\u9e1f","\u76bf","\u7f52","\u7acb","\u767d","\u793a","\u76ae","\u77e2","\u7389","\u74dc","\u751f","\u7528","\u7518","\u758b","\u77db","\u7676","\u6bcd","\u7384","\u9f99","\u4e1a","\u6b7a","\u7c73<span>(6\u753b)<\/span>","\u821f","\u8033","\u7fbd","\u8863","\u9875","\u7cf9","\u7cf8","\u7f8a","\u8012","\u864d","\u7f36","\u884c","\u81fc","\u820c","\u8840","\u8089","\u8980","\u81ea","\u81f3","\u807f","\u81e3","\u8272","\u800c","\u826e","\u8278","\u7f51","\u9f50","\u5148","\u897f","\u8a00<span>(7\u753b)<\/span>","\u8db3","\u8eca","\u8c9d","\u9149","\u8d70","\u898b","\u89d2","\u8c78","\u8c55","\u8eab","\u8f9b","\u8c46","\u8c37","\u8d64","\u9091","\u9578","\u514b","\u8fb0","\u91cc","\u9ea6","\u5364","\u8fb5","\u91d2<span>(8\u753b)<\/span>","\u98e0","\u96e8","\u9c7c","\u9580","\u96b9","\u91d1","\u9f7f","\u9752","\u91c7","\u975e","\u96b6","\u9577","\u961c","\u9763","\u9751","\u9801<span>(9\u753b)<\/span>","\u9769","\u9aa8","\u98a8","\u9b3c","\u97cb","\u9999","\u97f3","\u9762","\u97ed","\u9996","\u98df","\u99ac<span>(10\u753b)<\/span>","\u9adf","\u9b25","\u9b32","\u9ad8","\u9b2f","\u9ce5<span>(11\u753b)<\/span>","\u9b5a","\u9e7f","\u9ea5","\u9ec4","\u9e75","\u9ebb","\u9ed1<span>(12\u753b)<\/span>","\u9efd","\u9f0e","\u9ef9","\u9ecd","\u9f20<span>(\u66f4\u591a)<\/span>","\u9f13","\u9f3b","\u9f4a","\u9f52","\u9f8d","\u9fa0"],"strokes":["\u5168\u90e8","1\u753b","2\u753b","3\u753b","4\u753b","5\u753b","6\u753b","7\u753b","8\u753b","9\u753b","10\u753b","11\u753b","12\u753b","13\u753b","14\u753b","15\u753b","16\u753b","17\u753b","18\u753b","19\u753b","20\u753b","21\u753b","22\u753b","23\u753b","24\u753b","25\u753b","26\u753b","27\u753b","28\u753b","29\u753b","30\u753b","31\u753b","32\u753b","33\u753b","34\u753b","35\u753b","36\u753b","37\u753b","38\u753b","39\u753b","40\u753b","41\u753b","42\u753b","43\u753b","44\u753b","45\u753b","46\u753b","47\u753b","48\u753b"],"line_type":["\u5168\u90e8","\u91d1","\u6728","\u6c34","\u706b","\u571f"]},"nameMapping":{"radicals":"\u90e8\u9996","strokes":"\u7b14\u753b","line_type":"\u4e94\u884c"},"activeTags":{"radicals":["\u5168\u90e8"],"strokes":["\u5168\u90e8"],"line_type":["\u91d1"]}},"result_type":"zici"}